resultite/__init__.py
resultite/core.py
resultite-0.1.0.dist-info/METADATA
resultite-0.1.0.dist-info/WHEEL
resultite-0.1.0.dist-info/top_level.txt
resultite-0.1.0.dist-info/RECORD
