Metadata-Version: 2.4
Name: resultite
Version: 0.1.0
Summary: Bloat free result type for Python. No dummy classes. Pure types magic.
Author-email: Lee Yurin <leeyurin@mail.nwpu.edu.cn>
Requires-Python: >=3.10
Provides-Extra: test
Requires-Dist: asyncio; extra == "test"
